{
  "date": "2026-04-18",
  "total_revenue": 5380.0,
  "total_spend": 0,
  "total_wechat": 24,
  "total_deposit": 5,
  "roi": 0,
  "roi_level": "danger",
  "city_matrix": {
    "成都": {
      "spend": 0,
      "open": 0,
      "wechat": 9,
      "open_to_wechat": 0,
      "deposit": 5,
      "wechat_to_deposit": 55.6,
      "revenue": 5380.0,
      "refund_count": 0,
      "open_cost": 0
    },
    "重庆": {
      "spend": 0,
      "open": 0,
      "wechat": 0,
      "open_to_wechat": 0,
      "deposit": 0,
      "wechat_to_deposit": 0,
      "revenue": 0.0,
      "refund_count": 0,
      "open_cost": 0
    },
    "哈尔滨": {
      "spend": 0,
      "open": 0,
      "wechat": 15,
      "open_to_wechat": 0,
      "deposit": 0,
      "wechat_to_deposit": 0.0,
      "revenue": 0.0,
      "refund_count": 0,
      "open_cost": 0
    }
  },
  "acquire_chain": {
    "open": 0,
    "wechat": 24,
    "deposit": 5,
    "open_to_wechat": 0,
    "wechat_to_deposit": 20.8
  },
  "deliver_chain": {
    "expected": 3,
    "arrived": 3,
    "revenue": 5380.0,
    "arrival_rate": 100.0
  },
  "national_blacklist": [
    {
      "client": "王珊",
      "problem": "回访",
      "type": "未完成",
      "cs": "会媛",
      "level": "warning",
      "city": "成都"
    },
    {
      "client": "赵心宁",
      "problem": "回访",
      "type": "未完成",
      "cs": "会媛",
      "level": "warning",
      "city": "成都"
    },
    {
      "client": "郭尔惠",
      "problem": "回访",
      "type": "未完成",
      "cs": "阳珂欣",
      "level": "warning",
      "city": "成都"
    },
    {
      "client": "潘灿",
      "problem": "回访",
      "type": "未完成",
      "cs": "阳珂欣",
      "level": "warning",
      "city": "成都"
    },
    {
      "client": "马青秀",
      "problem": "回访",
      "type": "未完成",
      "cs": "阳珂欣",
      "level": "warning",
      "city": "成都"
    },
    {
      "client": "薛小胖",
      "problem": "回访",
      "type": "未完成",
      "cs": "阳珂欣",
      "level": "warning",
      "city": "成都"
    },
    {
      "client": "张诗若",
      "problem": "回访",
      "type": "未完成",
      "cs": "阳珂欣",
      "level": "warning",
      "city": "成都"
    },
    {
      "client": "周小琳",
      "problem": "回访",
      "type": "未完成",
      "cs": "会媛",
      "level": "warning",
      "city": "成都"
    }
  ],
  "city_open_cost": {
    "成都": 0,
    "重庆": 0,
    "哈尔滨": 0
  },
  "open_cost_redline": 80,
  "ai_national_summary": "1. 🏆 成都变现¥5380.0，表现最佳。\n\n2. 🚨 重庆各项指标均为0，建议加强营销。\n\n3. ⚠️ 交付端全绿，无退款或爽约。"
}